{"images":[{"startdate":"20181216","fullstartdate":"201812161600","enddate":"20181217","url":"/az/hprichbg/rb/OsoyoosExpressway_ZH-CN12997739047_1920x1080.jpg","urlbase":"/az/hprichbg/rb/OsoyoosExpressway_ZH-CN12997739047","copyright":"长曝光摄影下的奥索尤斯小镇车流 (© Bun Lee/Media Drum World/Aurora Photos)","copyrightlink":"http://www.bing.com/search?q=%E5%8A%A0%E6%8B%BF%E5%A4%A7%EF%BC%8C%E8%8B%B1%E5%B1%9E%E5%93%A5%E4%BC%A6%E6%AF%94%E4%BA%9A&form=HPCAPT&mkt=zh-cn","title":"","quiz":"/search?q=Bing+homepage+quiz&filters=WQOskey:%22HPQuiz_20181216_OsoyoosExpressway%22&FORM=HPQUIZ","wp":true,"hsh":"1ed95a0b9026f25fd5dda0686ca14534","drk":1,"top":1,"bot":1,"hs":[]}],"tooltips":{"loading":"正在加载...","previous":"上一个图像","next":"下一个图像","walle":"此图片不能下载用作壁纸。","walls":"下载今日美图。仅限用作桌面壁纸。"}}