{"images":[{"startdate":"20180322","fullstartdate":"201803221600","enddate":"20180323","url":"/az/hprichbg/rb/PeruCanyonClouds_ZH-CN10405307621_1920x1080.jpg","urlbase":"/az/hprichbg/rb/PeruCanyonClouds_ZH-CN10405307621","copyright":"【今日世界气象日】秘鲁太平洋沿岸Yauca和Acarí河上空的云层 (© Joshua Stevens/NASA)","copyrightlink":"http://www.bing.com/search?q=%E4%B8%96%E7%95%8C%E6%B0%94%E8%B1%A1%E6%97%A5&form=hpcapt&mkt=zh-cn","quiz":"/search?q=Bing+homepage+quiz&filters=WQOskey:%22HPQuiz_20180322_PeruCanyonClouds%22&FORM=HPQUIZ","wp":false,"hsh":"d806a9b1210db416eeb562fa0ab3bd4d","drk":1,"top":1,"bot":1,"hs":[]}],"tooltips":{"loading":"正在加载...","previous":"上一个图像","next":"下一个图像","walle":"此图片不能下载用作壁纸。","walls":"下载今日美图。仅限用作桌面壁纸。"}}