{"images":[{"startdate":"20201227","fullstartdate":"202012271600","enddate":"20201228","url":"/th?id=OHR.CanadaLynx_ZH-CN8645816958_1920x1080.jpg&rf=LaDigue_1920x1080.jpg&pid=hp","urlbase":"/th?id=OHR.CanadaLynx_ZH-CN8645816958","copyright":"加拿大猞猁，蒙大拿州 (© Alan and Sandy Carey/Minden Pictures)","copyrightlink":"https://www.bing.com/search?q=%E5%8A%A0%E6%8B%BF%E5%A4%A7%E7%8C%9E%E7%8C%81&form=hpcapt&mkt=zh-cn","title":"","quiz":"/search?q=Bing+homepage+quiz&filters=WQOskey:%22HPQuiz_20201227_CanadaLynx%22&FORM=HPQUIZ","wp":true,"hsh":"9213805c3f0f6bbebd73215c10cc3396","drk":1,"top":1,"bot":1,"hs":[]}],"tooltips":{"loading":"正在加载...","previous":"上一个图像","next":"下一个图像","walle":"此图片不能下载用作壁纸。","walls":"下载今日美图。仅限用作桌面壁纸。"}}