{"images":[{"startdate":"20220207","fullstartdate":"202202071600","enddate":"20220208","url":"/th?id=OHR.SpeloncatoSnow_ZH-CN8115437163_1920x1080.jpg&rf=LaDigue_1920x1080.jpg&pid=hp","urlbase":"/th?id=OHR.SpeloncatoSnow_ZH-CN8115437163","copyright":"科西嘉岛上的Speloncato市，法国 (© Jon Ingall/Alamy)","copyrightlink":"https://www.bing.com/search?q=%E7%A7%91%E8%A5%BF%E5%98%89%E5%B2%9B&form=hpcapt&mkt=zh-cn","title":"拿破仑在这里出生","quiz":"/search?q=Bing+homepage+quiz&filters=WQOskey:%22HPQuiz_20220207_SpeloncatoSnow%22&FORM=HPQUIZ","wp":true,"hsh":"e78a049cd7a69c7e67bab00403802733","drk":1,"top":1,"bot":1,"hs":[]}],"tooltips":{"loading":"正在加载...","previous":"上一个图像","next":"下一个图像","walle":"此图片不能下载用作壁纸。","walls":"下载今日美图。仅限用作桌面壁纸。"}}